{"nodes": [{"id": "ui_src_pages_runloader_tsx", "label": "RunLoader.tsx", "file_type": "code", "source_file": "ui/src/pages/RunLoader.tsx", "source_location": "L1"}, {"id": "runloader_fetchruns", "label": "fetchRuns()", "file_type": "code", "source_file": "ui/src/pages/RunLoader.tsx", "source_location": "L23"}, {"id": "runloader_handleupload", "label": "handleUpload()", "file_type": "code", "source_file": "ui/src/pages/RunLoader.tsx", "source_location": "L39"}, {"id": "runloader_handlenewrunsuccess", "label": "handleNewRunSuccess()", "file_type": "code", "source_file": "ui/src/pages/RunLoader.tsx", "source_location": "L60"}], "edges": [{"source": "ui_src_pages_runloader_tsx", "target": "react", "relation": "imports_from", "confidence": "EXTRACTED", "source_file": "ui/src/pages/RunLoader.tsx", "source_location": "L1", "weight": 1.0}, {"source": "ui_src_pages_runloader_tsx", "target": "react_router_dom", "relation": "imports_from", "confidence": "EXTRACTED", "source_file": "ui/src/pages/RunLoader.tsx", "source_location": "L2", "weight": 1.0}, {"source": "ui_src_pages_runloader_tsx", "target": "ui_src_store_runstore", "relation": "imports_from", "confidence": "EXTRACTED", "source_file": "ui/src/pages/RunLoader.tsx", "source_location": "L3", "weight": 1.0}, {"source": "ui_src_pages_runloader_tsx", "target": "ui_src_components_filterbar", "relation": "imports_from", "confidence": "EXTRACTED", "source_file": "ui/src/pages/RunLoader.tsx", "source_location": "L4", "weight": 1.0}, {"source": "ui_src_pages_runloader_tsx", "target": "ui_src_components_newrundialog", "relation": "imports_from", "confidence": "EXTRACTED", "source_file": "ui/src/pages/RunLoader.tsx", "source_location": "L5", "weight": 1.0}, {"source": "ui_src_pages_runloader_tsx", "target": "ui_src_types_autored", "relation": "imports_from", "confidence": "EXTRACTED", "source_file": "ui/src/pages/RunLoader.tsx", "source_location": "L6", "weight": 1.0}, {"source": "ui_src_pages_runloader_tsx", "target": "ui_src_utils_normalizerun", "relation": "imports_from", "confidence": "EXTRACTED", "source_file": "ui/src/pages/RunLoader.tsx", "source_location": "L7", "weight": 1.0}, {"source": "ui_src_pages_runloader_tsx", "target": "runloader_fetchruns", "relation": "contains", "confidence": "EXTRACTED", "source_file": "ui/src/pages/RunLoader.tsx", "source_location": "L23", "weight": 1.0}, {"source": "ui_src_pages_runloader_tsx", "target": "runloader_handleupload", "relation": "contains", "confidence": "EXTRACTED", "source_file": "ui/src/pages/RunLoader.tsx", "source_location": "L39", "weight": 1.0}, {"source": "ui_src_pages_runloader_tsx", "target": "runloader_handlenewrunsuccess", "relation": "contains", "confidence": "EXTRACTED", "source_file": "ui/src/pages/RunLoader.tsx", "source_location": "L60", "weight": 1.0}, {"source": "runloader_handleupload", "target": "runloader_fetchruns", "relation": "calls", "confidence": "EXTRACTED", "source_file": "ui/src/pages/RunLoader.tsx", "source_location": "L51", "weight": 1.0}, {"source": "runloader_handlenewrunsuccess", "target": "runloader_fetchruns", "relation": "calls", "confidence": "EXTRACTED", "source_file": "ui/src/pages/RunLoader.tsx", "source_location": "L62", "weight": 1.0}], "raw_calls": [{"caller_nid": "runloader_fetchruns", "callee": "fetch", "source_file": "ui/src/pages/RunLoader.tsx", "source_location": "L25"}, {"caller_nid": "runloader_fetchruns", "callee": "normalizeRunList", "source_file": "ui/src/pages/RunLoader.tsx", "source_location": "L27"}, {"caller_nid": "runloader_fetchruns", "callee": "json", "source_file": "ui/src/pages/RunLoader.tsx", "source_location": "L27"}, {"caller_nid": "runloader_fetchruns", "callee": "setRuns", "source_file": "ui/src/pages/RunLoader.tsx", "source_location": "L28"}, {"caller_nid": "runloader_fetchruns", "callee": "setFilteredRuns", "source_file": "ui/src/pages/RunLoader.tsx", "source_location": "L29"}, {"caller_nid": "runloader_fetchruns", "callee": "setError", "source_file": "ui/src/pages/RunLoader.tsx", "source_location": "L30"}, {"caller_nid": "runloader_fetchruns", "callee": "error", "source_file": "ui/src/pages/RunLoader.tsx", "source_location": "L32"}, {"caller_nid": "runloader_fetchruns", "callee": "setError", "source_file": "ui/src/pages/RunLoader.tsx", "source_location": "L33"}, {"caller_nid": "runloader_fetchruns", "callee": "setLoading", "source_file": "ui/src/pages/RunLoader.tsx", "source_location": "L35"}, {"caller_nid": "runloader_handleupload", "callee": "setUploading", "source_file": "ui/src/pages/RunLoader.tsx", "source_location": "L42"}, {"caller_nid": "runloader_handleupload", "callee": "append", "source_file": "ui/src/pages/RunLoader.tsx", "source_location": "L44"}, {"caller_nid": "runloader_handleupload", "callee": "fetch", "source_file": "ui/src/pages/RunLoader.tsx", "source_location": "L46"}, {"caller_nid": "runloader_handleupload", "callee": "catch", "source_file": "ui/src/pages/RunLoader.tsx", "source_location": "L48"}, {"caller_nid": "runloader_handleupload", "callee": "json", "source_file": "ui/src/pages/RunLoader.tsx", "source_location": "L48"}, {"caller_nid": "runloader_handleupload", "callee": "error", "source_file": "ui/src/pages/RunLoader.tsx", "source_location": "L53"}, {"caller_nid": "runloader_handleupload", "callee": "setError", "source_file": "ui/src/pages/RunLoader.tsx", "source_location": "L54"}, {"caller_nid": "runloader_handleupload", "callee": "setUploading", "source_file": "ui/src/pages/RunLoader.tsx", "source_location": "L56"}, {"caller_nid": "runloader_handlenewrunsuccess", "callee": "setShowNewRun", "source_file": "ui/src/pages/RunLoader.tsx", "source_location": "L61"}]}